rlaehgus97_cli/__init__.py
rlaehgus97_cli/cli.py
rlaehgus97_cli-0.1.2.dist-info/METADATA
rlaehgus97_cli-0.1.2.dist-info/WHEEL
rlaehgus97_cli-0.1.2.dist-info/entry_points.txt
rlaehgus97_cli-0.1.2.dist-info/top_level.txt
rlaehgus97_cli-0.1.2.dist-info/RECORD
