Metadata-Version: 2.1
Name: rlaehgus97_cli
Version: 0.1.2
Summary: Default template for PDM package
Author-email: rlaehgus97 <starkim625@gmail.com>
License: MIT
Requires-Python: >=3.9
Requires-Dist: rlaehgus97-lotto >=0.2.0
